deepsegment/__init__.py
deepsegment/deepsegment.py
deepsegment/train.py
deepsegment-2.3.1.dist-info/LICENSE
deepsegment-2.3.1.dist-info/METADATA
deepsegment-2.3.1.dist-info/WHEEL
deepsegment-2.3.1.dist-info/top_level.txt
deepsegment-2.3.1.dist-info/RECORD
