Metadata-Version: 2.1
Name: deepsegment
Version: 2.3.1
Summary: Sentence Segmentation with sequece tagging
Home-page: https://github.com/bedapudi6788/Deep-Segmentation
Author: BEDAPUDI PRANEETH
Author-email: praneeth@bpraneeth.com
License: GPLv3
Platform: UNKNOWN
Classifier: License :: OSI Approved :: GNU General Public License v3 (GPLv3)
Classifier: Programming Language :: Python
Classifier: Programming Language :: Python :: 3
Classifier: Programming Language :: Python :: 3.6
Classifier: Programming Language :: Python :: Implementation :: CPython
Classifier: Programming Language :: Python :: Implementation :: PyPy
Requires-Python: >=3.5.0
Requires-Dist: seqtag-keras
Requires-Dist: pydload
Requires-Dist: progressbar2
